{
    "name": "FO-GESR Acta de Visita de Supervisión en Planta o Bodega - Seguridad Alimentaria",
    "questions": [ 
        {
            "id": 1,
            "type": "text",
            "order": 1,
            "label": "Contratista",
            "options": [],
            "answer": ""
          },
          {
            "id": 2,
            "type": "text",
            "order": 1,
            "label": "Operador",
            "options": [],
            "answer": ""
          },
          {
            "id": 3,
            "type": "text",
            "order": 1,
            "label": "Codigo",
            "options": [],
            "answer": ""
          },
          {
            "id": 4,
            "type": "text",
            "order": 1,
            "label": "Bodega",
            "options": [],
            "answer": ""
          },
          {
            "id": 5,
            "type": "multi-question",
            "order": 1,
            "label": "Modalidad de Atencion",
            "innerQuestions": [
              {
                "label": "Complemento Tipo Almuerzo",
                "answer": ""
              },
              {
                "label": "Racion Industrializada",
                "answer": ""
              },
              {
                "label": "Vaso de Leche",
                "answer": ""
              },
              {
                "label": "Racion de Contingencia",
                "answer": ""
              }
            ],
            "options": [
              "SI",
              "NO"
            ]
          },
          {
            "id": 6,
            "type": "option",
            "order": 1,
            "label": "Concepto de Secretaria de Salud o INVIMA",
            "options": [
              "No Tiene",
              "Favorable",
              "Condicionado"
            ],
            "answer": ""
          },
          {
            "id": 7,
            "type": "date",
            "order": 1,
            "label": "Fecha de Concepto",
            "options": [],
            "answer": ""
          },
          {
            "id": 8,
            "type": "text",
            "order": 1,
            "label": "Periodo o Mes Evaluado",
            "options": [],
            "answer": ""
          },
          {
            "id": 9,
            "type": "text",
            "order": 1,
            "label": "Nombre del Supervisor",
            "options": [],
            "answer": ""
          },
          {
            "id": 10,
            "type": "label",
            "order": 1,
            "label": "Procesos Realizados"
          },
          {
            "id": 11,
            "type": "date",
            "order": 1,
            "label": "Fecha de Visita",
            "options": [],
            "answer": ""
          },
          {
            "id": 12,
            "type": "text",
            "order": 1,
            "label": "Verificacion de Materia Prima",
            "options": [],
            "answer": ""
          },
          {
            "id": 13,
            "type": "text",
            "order": 1,
            "label": "Condiociones Higienico-Sanitarias",
            "options": [],
            "answer": ""
          },
          {
            "id": 14,
            "type": "text",
            "order": 1,
            "label": "Socializacion de Hallazgos ",
            "options": [],
            "answer": ""
          },
          {
            "id": 15,
            "type": "text",
            "order": 1,
            "label": "Control Metrologico",
            "options": [],
            "answer": ""
          },
          {
            "id": 16,
            "type": "text",
            "order": 1,
            "label": "Seguimiento a Personal o Vehiculos",
            "options": [],
            "answer": ""
          },
          {
            "id": 17,
            "type": "text",
            "order": 1,
            "label": "Regostro de la Bitacora",
            "options": [],
            "answer": ""
          },
          {
            "id": 18,
            "type": "text",
            "order": 1,
            "label": "Rastreo Fisico-Quimico o Microbilogico",
            "options": [],
            "answer": ""
          }

    ]
}